{
  "problem_list": [
    {
      "A_matrix": [
        [
          2,
          0,
          0,
          4
        ],
        [
          0,
          2,
          0,
          0
        ],
        [
          0,
          0,
          2,
          0
        ],
        [
          4,
          0,
          0,
          2
        ]
      ],
      "b_vector": [
        0.3713906763541037,
        0.7427813527082074,
        0.0,
        0.5570860145311556
      ]
    }
  ],
  "shots": 3000,
  "backend": "sv1",
  "device_arn": "SV1",
  "aws_region": "eu-west-2",
  "problem_source": "custom_4x4_problem.json",
  "ideal_preprocessing_list": [
    [
      [
        -2.0,
        2.0,
        2.0,
        6.0
      ],
      [
        0.13130643285972254,
        0.0,
        0.7427813527082074,
        0.6565321642986128
      ]
    ]
  ],
  "probability_threshold": 0,
  "k_qubits": 8,
  "projection_mode": "all_components",
  "projection_subset": null,
  "num_solution_qubits": 2,
  "num_projections": 4,
  "projector_basis_states": [
    0,
    1,
    2,
    3
  ],
  "enhanced_projection_results": [
    {
      "problem_index": 0,
      "projection_tasks": [
        {
          "basis_state": 0,
          "task_id": "arn:aws:braket:eu-west-2:380012739362:quantum-task/ed3a2f8d-7f6d-478a-9ba2-6e143f6f52bf",
          "status": "DONE",
          "shots": 3000,
          "counts": {
            "01000000001": 1139,
            "00000000000": 509,
            "01110000000": 152,
            "11000000000": 664,
            "01110000001": 164,
            "01101000000": 36,
            "01000000000": 55,
            "00000000001": 151,
            "11100000001": 10,
            "01101000001": 33,
            "01010000000": 4,
            "01100100000": 5,
            "00010000000": 1,
            "11101000000": 1,
            "01100000001": 4,
            "01001000001": 3,
            "00100000001": 1,
            "01100000000": 5,
            "01011000000": 3,
            "01010000001": 7,
            "01100100001": 6,
            "01100010000": 4,
            "11110000001": 7,
            "11000000001": 9,
            "01100010001": 3,
            "00000100001": 1,
            "11010000001": 5,
            "01011000001": 4,
            "01001000000": 2,
            "01100001000": 1,
            "00100100000": 1,
            "01010100000": 2,
            "01100001001": 1,
            "00100000000": 1,
            "01100000101": 2,
            "01010100001": 1,
            "01111000001": 1,
            "11101000001": 1,
            "11001000001": 1
          },
          "component_probability": 0.09845559845559845,
          "success_rate": 0.518
        },
        {
          "basis_state": 1,
          "task_id": "arn:aws:braket:eu-west-2:380012739362:quantum-task/f6db9767-0a9a-4acc-90ce-c04ffe6d024b",
          "status": "DONE",
          "shots": 3000,
          "counts": {
            "00000000000": 561,
            "01000000001": 1143,
            "01110000001": 160,
            "11000000000": 603,
            "01110000000": 155,
            "11000000001": 11,
            "00000000001": 133,
            "01101000000": 43,
            "01101000001": 49,
            "01100100001": 8,
            "01100000001": 9,
            "01010000000": 8,
            "01100100000": 10,
            "01001000001": 3,
            "01000000000": 41,
            "11000100001": 1,
            "01100000000": 12,
            "01100010001": 2,
            "01011000000": 6,
            "00101000001": 2,
            "01110100000": 1,
            "00100100000": 2,
            "11100000001": 2,
            "11110000001": 2,
            "11010000001": 2,
            "01001000000": 1,
            "00001000001": 1,
            "01010000001": 4,
            "00100100001": 1,
            "00010000001": 1,
            "01011000001": 2,
            "00110000000": 2,
            "00110000001": 3,
            "01100001001": 1,
            "01100010000": 2,
            "00100000001": 2,
            "11100100001": 2,
            "01010100000": 2,
            "01010010000": 1,
            "11110000000": 2,
            "01010100001": 1,
            "01010010001": 1,
            "01001100000": 1,
            "11001000001": 1
          },
          "component_probability": 0.0,
          "success_rate": 0.5156666666666667
        },
        {
          "basis_state": 2,
          "task_id": "arn:aws:braket:eu-west-2:380012739362:quantum-task/1854198c-ea29-4dd5-95ad-6e1621b00b93",
          "status": "DONE",
          "shots": 3000,
          "counts": {
            "01000000001": 1128,
            "11000000000": 622,
            "00000000001": 137,
            "00000000000": 581,
            "01110000000": 164,
            "01010000001": 7,
            "01000000000": 47,
            "01110000001": 148,
            "11100000001": 3,
            "01101000001": 29,
            "01100100001": 15,
            "00010000001": 1,
            "01100000001": 5,
            "01101000000": 36,
            "01011000001": 7,
            "01011000000": 7,
            "11000000001": 12,
            "11110000001": 4,
            "01010100000": 1,
            "00001000001": 1,
            "01111000001": 3,
            "01100100000": 14,
            "00111000001": 1,
            "00110000001": 1,
            "01100000000": 4,
            "11101000000": 2,
            "11010000001": 1,
            "01010000000": 2,
            "01001000001": 1,
            "01000100000": 2,
            "01010100001": 1,
            "01100010000": 2,
            "01100010001": 2,
            "01100001000": 1,
            "00100000001": 1,
            "00110000000": 1,
            "11100100001": 1,
            "11110000000": 1,
            "01100001001": 2,
            "00101000000": 1,
            "11011000000": 1
          },
          "component_probability": 0.8921244209133025,
          "success_rate": 0.5036666666666667
        },
        {
          "basis_state": 3,
          "task_id": "arn:aws:braket:eu-west-2:380012739362:quantum-task/8917ad02-a54b-423f-8a68-bed3f1122f66",
          "status": "DONE",
          "shots": 3000,
          "counts": {
            "11000000000": 621,
            "00000000001": 143,
            "01110000000": 149,
            "01000000001": 1126,
            "01100000100": 2,
            "01110000001": 176,
            "00000000000": 529,
            "11110000001": 6,
            "01101000001": 45,
            "01010010000": 2,
            "00110000001": 3,
            "01101000000": 35,
            "11010000001": 4,
            "01000000000": 46,
            "01010000001": 7,
            "01100100000": 12,
            "11000000001": 14,
            "01001010101": 1,
            "01011000001": 4,
            "01100100001": 18,
            "00010000001": 5,
            "11100000001": 4,
            "01010001000": 1,
            "00110000000": 5,
            "01001100000": 1,
            "01100000000": 9,
            "01100010001": 2,
            "01010100001": 3,
            "01011000000": 6,
            "01010000000": 5,
            "01010100000": 2,
            "01100000001": 6,
            "01100010000": 2,
            "00010000000": 2,
            "00011000000": 1,
            "11110000000": 2,
            "11010010000": 1
          },
          "component_probability": 0.017868538608806637,
          "success_rate": 0.5223333333333333
        }
      ],
      "depth": 1575,
      "num_projections": 4,
      "ideal_solution": [
        {
          "real": 0.31524416249564025,
          "imag": 0.0
        },
        {
          "real": 0.9457324874869207,
          "imag": 0.0
        },
        {
          "real": 0.0,
          "imag": 0.0
        },
        {
          "real": 0.07881104062391006,
          "imag": 0.0
        }
      ],
      "reconstructed_solution_probabilities": [
        0.09763075932503329,
        0.0,
        0.8846504007128775,
        0.017718839962089204
      ],
      "fidelity": 0.011879179422439013,
      "metadata": {
        "measured_components": [
          0,
          1,
          2,
          3
        ],
        "success_rates": [
          0.518,
          0.5156666666666667,
          0.5036666666666667,
          0.5223333333333333
        ],
        "raw_probabilities": [
          0.09845559845559845,
          0.0,
          0.8921244209133025,
          0.017868538608806637
        ],
        "average_success_rate": 0.5149166666666667,
        "total_probability": 1.0084485579777076
      }
    }
  ]
}